{
  "id": "20260802",
  "title": "ええじゃないか４",
  "date": "2026/08/02 (日)",
  "timeStart": "17:00",
  "timeEnd": "22:30",
  "flyer": "images/flyer1.png",
  "flyerAlt": "images/flyer2.png",
  "timetableFile": "data/20260802.json",
  "copy": [
    "トランス、パンク、ヒップホップ、",
    "昭和歌謡、シティポップ…",
    "",
    "ジャンルの壁をぶっ壊す",
    "ダンスパーティーが白楽に帰ってきた。",
    "",
    "週末DJ極楽とんぼ。踊る君はスパイシー。",
    "なんて素敵なファンキーナイト。",
    "ごった煮のクレオール。わくわく白楽。"
  ],
  "venue": "Cafe doudou（フーウンカオルジョー2号店）",
  "address": "神奈川県横浜市神奈川区白楽100-11-103",
  "walkTime": "白楽駅から徒歩１分",
  "fee": "¥1,000（ドリンク別）",
  "note": "時間あれば飛び入りDJ可能！",
  "genres": [
    {"name":"トランス","color":"g-trance"},
    {"name":"パンク","color":"g-punk"},
    {"name":"ヒップホップ","color":"g-hiphop"},
    {"name":"昭和歌謡","color":"g-showa"},
    {"name":"シティポップ","color":"g-city"},
    {"name":"なんでもあり","color":"g-oshare"}
  ],
  "mapUrl": "https://maps.google.com/?q=横浜市神奈川区白楽",
  "area": {
    "name": "白楽（はくら）",
    "desc": "東横線の各停だけ停まる穴場駅。昔ながらの商店街が残る下町エリア。\n駅前の白楽銀座商店街を抜けると、綱島街道沿いに会場のCAFE doudou。\n途中にまちだ図書館や広尾橋があり、散歩にぴったりのルートです。",
    "spots": [
      {"icon":"🍜","name":"白楽銀座商店街"},
      {"icon":"📚","name":"まちだ図書館"},
      {"icon":"🌉","name":"広尾橋"},
      {"icon":"☕","name":"サイダーバー白楽"}
    ]
  },
  "sanpo": {
    "route": "白楽駅 → まちだ図書館 → 広尾橋 → サイダーバー白楽",
    "meeting": "16:00 白楽駅改札前",
    "departure": "16:05",
    "arrival": "17:00 サイダーバー白楽",
    "distance": "約2.5km",
    "difficulty": "★☆☆ 誰でも",
    "checklist": ["水分（500ml以上）","帽子","日焼け止め","歩きやすい靴","スマートフォン","財布・ICカード"]
  },
  "members": [
    {
      "name": "TOMSUCK",
      "genre": "トランス",
      "links": [
        {"label":"Instagram","url":"https://www.instagram.com/tomsuck_jp/"},
        {"label":"Twitter/X","url":"https://twitter.com/tomsuck"},
        {"label":"note","url":"https://note.com/tomsuck"},
        {"label":"hearthis.at","url":"https://hearthis.at/tomsuck/"},
        {"label":"lit.link","url":"https://lit.link/rArs48z21rVQPVhtu0LxdSOCQX72"}
      ],
      "bio": "本籍はトランス、住所はサイケ、グルーヴはハウス、魂はテクノのレイヴ民。元ガバっ子。90年代テクノパーティー「X-TEND」主催。2023年にVRデビュー。"
    },
    {
      "name": "ALKA",
      "genre": "トランス",
      "links": [{"label":"Instagram","url":"https://www.instagram.com/alka611o/"}]
    },
    {
      "name": "Haraken",
      "genre": "インディロック",
      "links": [{"label":"Instagram","url":"https://www.instagram.com/musik_drunc/"}]
    },
    {
      "name": "オレンジさん",
      "genre": "パンク",
      "links": [{"label":"Instagram","url":"https://www.instagram.com/orengechanwada/"}]
    },
    {
      "name": "あなるちゃん",
      "genre": "アニメーション",
      "links": [{"label":"Instagram","url":"https://www.instagram.com/analchan/"}]
    },
    {
      "name": "ムッシュ",
      "genre": "昭和歌謡",
      "links": [{"label":"Instagram","url":"https://www.instagram.com/bistro_la_zic.yokohama3/"}]
    },
    {
      "name": "おしゃれどろぼう",
      "genre": "ヒップホップ",
      "links": [{"label":"Instagram","url":"https://www.instagram.com/oshare.dorobous/"}]
    },
    {
      "name": "犬八朗",
      "genre": "シティポップ",
      "links": [{"label":"Instagram","url":"https://www.instagram.com/inuhachiro/"}]
    }
  ]
}
